pyhip/__init__.py
pyhip/hip.py
pyhip/hiprtc.py
pyhip_interface-0.1.1.dist-info/LICENSE
pyhip_interface-0.1.1.dist-info/METADATA
pyhip_interface-0.1.1.dist-info/WHEEL
pyhip_interface-0.1.1.dist-info/top_level.txt
pyhip_interface-0.1.1.dist-info/RECORD
