Metadata-Version: 2.1
Name: pyhip-interface
Version: 0.1.1
Summary: Python Interface to HIP and hiprtc Library
Home-page: UNKNOWN
Author: Jatin Chaudhary
Author-email: ndjatin@gmail.com
License: UNKNOWN
Project-URL: Source, https://github.com/jatinx/PyHIP
Keywords: HIP GPU parallel computing scientific computing Python wrapper
Platform: UNKNOWN
License-File: LICENSE
